<annotation>
	<folder>王金洲</folder>
	<filename>1.2.826.0.1.3680043.2.461.11533100.4180559000.jpg</filename>
	<path>C:\Users\LoTvT\Desktop\肌瘤\王金洲\1.2.826.0.1.3680043.2.461.11533100.4180559000.jpg</path>
	<source>
		<database>Unknown</database>
	</source>
	<size>
		<width>1024</width>
		<height>768</height>
		<depth>3</depth>
	</size>
	<segmented>0</segmented>
	<object>
		<name>肌瘤</name>
		<pose>Unspecified</pose>
		<truncated>0</truncated>
		<difficult>0</difficult>
		<bndbox>
			<xmin>427</xmin>
			<ymin>391</ymin>
			<xmax>500</xmax>
			<ymax>446</ymax>
		</bndbox>
	</object>
</annotation>
