<annotation>
	<folder>陈菊花</folder>
	<filename>1.2.826.0.1.3680043.2.461.11838263.1938978640.jpg</filename>
	<path>D:\肌瘤\陈菊花\1.2.826.0.1.3680043.2.461.11838263.1938978640.jpg</path>
	<source>
		<database>Unknown</database>
	</source>
	<size>
		<width>1024</width>
		<height>768</height>
		<depth>3</depth>
	</size>
	<segmented>0</segmented>
	<object>
		<name>肌瘤</name>
		<pose>Unspecified</pose>
		<truncated>0</truncated>
		<difficult>0</difficult>
		<bndbox>
			<xmin>307</xmin>
			<ymin>465</ymin>
			<xmax>421</xmax>
			<ymax>561</ymax>
		</bndbox>
	</object>
</annotation>
